{"name": "Data + Utilities", "tweets": [{"link": "https://twitter.com/statuses/784363683313049600", "content": "<p class=\"TweetTextSize TweetTextSize--26px js-tweet-text tweet-text\" data-aria-label-part=\"0\" lang=\"en\">Get women to design products &amp; services end to end. End algorithmic bias. <a class=\"twitter-hashtag pretty-link js-nav\" data-query-source=\"hashtag_click\" dir=\"ltr\" href=\"http://www.twitter.com/hashtag/IODC16?src=hash\"><s>#</s><b>IODC16</b></a> <a class=\"twitter-hashtag pretty-link js-nav\" data-query-source=\"hashtag_click\" dir=\"ltr\" href=\"http://www.twitter.com/hashtag/opendata?src=hash\"><s>#</s><b>opendata</b></a><a class=\"twitter-timeline-link u-hidden\" data-pre-embedded=\"true\" dir=\"ltr\" href=\"https://t.co/4bwzR4covi\">pic.twitter.com/4bwzR4covi</a></p>"}, {"link": "https://twitter.com/statuses/784333720102670337", "content": "<p class=\"TweetTextSize TweetTextSize--26px js-tweet-text tweet-text\" data-aria-label-part=\"0\" lang=\"en\">Buenos Dias <a class=\"twitter-hashtag pretty-link js-nav\" data-query-source=\"hashtag_click\" dir=\"ltr\" href=\"http://www.twitter.com/hashtag/iodc16?src=hash\"><s>#</s><b>iodc16</b></a>! Let's talk about optimizing the business of government w data science. Deliver services effectively and efficiently.<a class=\"twitter-timeline-link u-hidden\" data-pre-embedded=\"true\" dir=\"ltr\" href=\"https://t.co/vK3x9bxapZ\">pic.twitter.com/vK3x9bxapZ</a></p>"}], "notes": "https://drive.google.com/open?id=18oKX_ssjQEuZQZKvNgCmvwDkhHud6OFBWWdDyG3_-bQ", "session": {"description": "\n Data + Utilities\n", "speakers": [{"profile": "/speaker/rafaelaguado", "speaker": "Rafael Aguado"}, {"profile": "/speaker/brianbanks2", "speaker": "Brian Banks"}, {"profile": "/speaker/pierrechrzanowski1", "speaker": "Pierre Chrzanowski"}, {"profile": "/speaker/antoniorodriguez1", "speaker": "Antonio Rodr\u00edguez"}, {"profile": "/moderator/fernandobelda", "speaker": "Fernando Belda"}]}, "photos": [], "youtube": "XtV8h5OiIqA"}