{"name": "Data + Inequality", "tweets": [{"link": "https://twitter.com/statuses/784379581331566592", "content": "<p class=\"TweetTextSize TweetTextSize--26px js-tweet-text tweet-text\" data-aria-label-part=\"0\" lang=\"en\">To scale <a class=\"twitter-hashtag pretty-link js-nav\" data-query-source=\"hashtag_click\" dir=\"ltr\" href=\"http://www.twitter.com/hashtag/opendata?src=hash\"><s>#</s><b>opendata</b></a> issues, need to focus on co-creation and linking data to persistent issues ~ corruption, inequality <a class=\"twitter-atreply pretty-link js-nav\" data-mentioned-user-id=\"216335805\" dir=\"ltr\" href=\"http://www.twitter.com/Fscrollini\"><s>@</s><b>Fscrollini</b></a> <a class=\"twitter-hashtag pretty-link js-nav\" data-query-source=\"hashtag_click\" dir=\"ltr\" href=\"http://www.twitter.com/hashtag/iodc16?src=hash\"><s>#</s><b>iodc16</b></a></p>"}, {"link": "https://twitter.com/statuses/784328425263599616", "content": "<p class=\"TweetTextSize TweetTextSize--26px js-tweet-text tweet-text\" data-aria-label-part=\"0\" lang=\"en\">Local bottom-up approach to <a class=\"twitter-hashtag pretty-link js-nav\" data-query-source=\"hashtag_click\" dir=\"ltr\" href=\"http://www.twitter.com/hashtag/opendata?src=hash\"><s>#</s><b>opendata</b></a> to involve communities and solve inequality issues in <a class=\"twitter-hashtag pretty-link js-nav\" data-query-source=\"hashtag_click\" dir=\"ltr\" href=\"http://www.twitter.com/hashtag/opendurban?src=hash\"><s>#</s><b>opendurban</b></a> <a class=\"twitter-hashtag pretty-link js-nav\" data-query-source=\"hashtag_click\" dir=\"ltr\" href=\"http://www.twitter.com/hashtag/IODC16?src=hash\"><s>#</s><b>IODC16</b></a><a class=\"twitter-timeline-link u-hidden\" data-pre-embedded=\"true\" dir=\"ltr\" href=\"https://t.co/knP4KFhOUZ\">pic.twitter.com/knP4KFhOUZ</a></p>"}, {"link": "https://twitter.com/statuses/784027451437481984", "content": "<p class=\"TweetTextSize TweetTextSize--26px js-tweet-text tweet-text\" data-aria-label-part=\"0\" lang=\"en\">Gender &amp; Numbers: How <a class=\"twitter-hashtag pretty-link js-nav\" data-query-source=\"hashtag_click\" dir=\"ltr\" href=\"http://www.twitter.com/hashtag/opendata?src=hash\"><s>#</s><b>opendata</b></a> can be used to tackle gender inequality in Brazil! Great talk at <a class=\"twitter-hashtag pretty-link js-nav\" data-query-source=\"hashtag_click\" dir=\"ltr\" href=\"http://www.twitter.com/hashtag/IODC16?src=hash\"><s>#</s><b>IODC16</b></a> by <a class=\"twitter-atreply pretty-link js-nav\" data-mentioned-user-id=\"16212914\" dir=\"ltr\" href=\"http://www.twitter.com/NataliaMazotte\"><s>@</s><b>NataliaMazotte</b></a> <a class=\"twitter-hashtag pretty-link js-nav\" data-query-source=\"hashtag_click\" dir=\"ltr\" href=\"http://www.twitter.com/hashtag/civiltech?src=hash\"><s>#</s><b>civiltech</b></a></p>"}], "notes": "https://drive.google.com/open?id=1AdYIiZcuaPsgLl-I3KsT_drCVHHckMsJr8gj6i1NaXQ", "session": {"description": "\n Data + Inequality\n", "speakers": [{"profile": "/speaker/nataliamazotte", "speaker": "Natalia Mazotte"}, {"profile": "/speaker/karenrono", "speaker": "Karen Rono"}, {"profile": "/moderator/lejlasadiku", "speaker": "Lejla Sadiku"}]}, "photos": [], "youtube": "aAB1q2sEQbw"}